colourtools/__init__.py
colourtools/adjustments.py
colourtools/converters.py
colourtools-0.1.2.1.dist-info/LICENSE
colourtools-0.1.2.1.dist-info/METADATA
colourtools-0.1.2.1.dist-info/WHEEL
colourtools-0.1.2.1.dist-info/RECORD
