Metadata-Version: 2.3
Name: colourtools
Version: 0.1.2.1
Summary: colourtools is a lightweight Python library for intuitive conversion and manipulation of colours across multiple formats
Author: Albert Pang
Author-email: alpaaccount@mac.com
Requires-Python: >=3.12
Classifier: Programming Language :: Python :: 3
Classifier: Programming Language :: Python :: 3.12
Classifier: Programming Language :: Python :: 3.13
Provides-Extra: examples
Project-URL: Homepage, https://github.com/alpaalpa/colourtools
Project-URL: Repository, https://github.com/alpaalpa/colourtools
